odoo/addons/account_invoice_confirm_popup/README.rst
odoo/addons/account_invoice_confirm_popup/__init__.py
odoo/addons/account_invoice_confirm_popup/__manifest__.py
odoo/addons/account_invoice_confirm_popup/i18n/account_invoice_confirm_popup.pot
odoo/addons/account_invoice_confirm_popup/i18n/fr.po
odoo/addons/account_invoice_confirm_popup/readme/CONFIGURE.rst
odoo/addons/account_invoice_confirm_popup/readme/CONTRIBUTORS.rst
odoo/addons/account_invoice_confirm_popup/readme/DESCRIPTION.rst
odoo/addons/account_invoice_confirm_popup/static/description/icon.png
odoo/addons/account_invoice_confirm_popup/static/description/index.html
odoo/addons/account_invoice_confirm_popup/views/account_invoice_view.xml
odoo12_addon_account_invoice_confirm_popup-12.0.1.0.0.99.dev4.dist-info/METADATA
odoo12_addon_account_invoice_confirm_popup-12.0.1.0.0.99.dev4.dist-info/WHEEL
odoo12_addon_account_invoice_confirm_popup-12.0.1.0.0.99.dev4.dist-info/top_level.txt
odoo12_addon_account_invoice_confirm_popup-12.0.1.0.0.99.dev4.dist-info/RECORD
